pixel/__init__.py
pixel/core/__init__.py
pixel/core/metadata.py
pixel/core/node.py
pixel/sdk/__init__.py
pixel/sdk/client.py
pixel/sdk/flow_decorator.py
pixel/sdk/node_flow.py
pixel/sdk/storage_client.py
pixel/sdk/models/__init__.py
pixel/sdk/models/node_decorator.py
pixel/sdk/models/vector2d.py
pixel/sdk/nodes/__init__.py
pixel/sdk/nodes/bilateral_filter_node.py
pixel/sdk/nodes/blur_node.py
pixel/sdk/nodes/box_filter_node.py
pixel/sdk/nodes/combine_node.py
pixel/sdk/nodes/floor_node.py
pixel/sdk/nodes/gaussian_blur_node.py
pixel/sdk/nodes/input_node.py
pixel/sdk/nodes/median_blur_node.py
pixel/sdk/nodes/output_file_node.py
pixel/sdk/nodes/output_node.py
pixel/sdk/nodes/resnet50_node.py
pixel/sdk/nodes/s3_input_node.py
pixel/sdk/nodes/s3_output_node.py
pixel/sdk/nodes/string_node.py
pixel/sdk/nodes/vector2d_node.py
pixel_sdk-1.0.25.dist-info/METADATA
pixel_sdk-1.0.25.dist-info/WHEEL
pixel_sdk-1.0.25.dist-info/top_level.txt
pixel_sdk-1.0.25.dist-info/RECORD
