Metadata-Version: 2.4
Name: pixel-sdk
Version: 1.0.25
Summary: Python client library for the pixel app
Author-email: pixel <polina@example.com>
Requires-Python: >=3.11
Requires-Dist: requests>=2.25.0
